slidingwindow/ArrayUtils.py
slidingwindow/Batching.py
slidingwindow/Merging.py
slidingwindow/RectangleUtils.py
slidingwindow/SlidingWindow.py
slidingwindow/WindowDistance.py
slidingwindow/__init__.py
slidingwindow-0.0.14.dist-info/LICENSE
slidingwindow-0.0.14.dist-info/METADATA
slidingwindow-0.0.14.dist-info/WHEEL
slidingwindow-0.0.14.dist-info/top_level.txt
slidingwindow-0.0.14.dist-info/zip-safe
slidingwindow-0.0.14.dist-info/RECORD
